<?xml version="1.0" ?>
<annotation>
    <folder>clothesRecognition</folder>
    <filename>711df9ad-a347-43bc-ac28-d865aaad5824.jpg</filename>
    <source>
        <database>My Database</database>
        <annotation>clothesRecognition</annotation>
        <image>flickr</image>
        <flickrid>NULL</flickrid>
    </source>
    <owner>
        <flickrid>NULL</flickrid>
        <name>idaneel</name>
    </owner>
    <size>
        <width>600</width>
        <height>600</height>
        <depth>3</depth>
    </size>
    <segmented>0</segmented>
    <object>
        <name>coat</name>
        <pose>Unspecified</pose>
        <truncated>0</truncated>
        <difficult>0</difficult>
        <bndbox>
            <xmin>142</xmin>
            <ymin>144</ymin>
            <xmax>559</xmax>
            <ymax>328</ymax>
        </bndbox>
    </object>
    <object>
        <name>pants</name>
        <pose>Unspecified</pose>
        <truncated>0</truncated>
        <difficult>0</difficult>
        <bndbox>
            <xmin>82</xmin>
            <ymin>293</ymin>
            <xmax>594</xmax>
            <ymax>462</ymax>
        </bndbox>
    </object>
    <object>
        <name>shoes</name>
        <pose>Unspecified</pose>
        <truncated>0</truncated>
        <difficult>0</difficult>
        <bndbox>
            <xmin>119</xmin>
            <ymin>449</ymin>
            <xmax>261</xmax>
            <ymax>567</ymax>
        </bndbox>
    </object>
    <object>
        <name>shoes</name>
        <pose>Unspecified</pose>
        <truncated>0</truncated>
        <difficult>0</difficult>
        <bndbox>
            <xmin>414</xmin>
            <ymin>442</ymin>
            <xmax>572</xmax>
            <ymax>571</ymax>
        </bndbox>
    </object>
</annotation>
