<?xml version="1.0" ?>
<annotation>
    <folder>clothesRecognition</folder>
    <filename>street_97.jpg</filename>
    <source>
        <database>My Database</database>
        <annotation>clothesRecognition</annotation>
        <image>flickr</image>
        <flickrid>NULL</flickrid>
    </source>
    <owner>
        <flickrid>NULL</flickrid>
        <name>idaneel</name>
    </owner>
    <size>
        <width>600</width>
        <height>600</height>
        <depth>3</depth>
    </size>
    <segmented>0</segmented>
    <object>
        <name>coat</name>
        <pose>Unspecified</pose>
        <truncated>0</truncated>
        <difficult>0</difficult>
        <bndbox>
            <xmin>217</xmin>
            <ymin>261</ymin>
            <xmax>349</xmax>
            <ymax>388</ymax>
        </bndbox>
    </object>
    <object>
        <name>pants</name>
        <pose>Unspecified</pose>
        <truncated>0</truncated>
        <difficult>0</difficult>
        <bndbox>
            <xmin>209</xmin>
            <ymin>376</ymin>
            <xmax>346</xmax>
            <ymax>543</ymax>
        </bndbox>
    </object>
    <object>
        <name>glasses</name>
        <pose>Unspecified</pose>
        <truncated>0</truncated>
        <difficult>0</difficult>
        <bndbox>
            <xmin>282</xmin>
            <ymin>219</ymin>
            <xmax>338</xmax>
            <ymax>247</ymax>
        </bndbox>
    </object>
    <object>
        <name>shoes</name>
        <pose>Unspecified</pose>
        <truncated>0</truncated>
        <difficult>0</difficult>
        <bndbox>
            <xmin>255</xmin>
            <ymin>529</ymin>
            <xmax>289</xmax>
            <ymax>560</ymax>
        </bndbox>
    </object>
    <object>
        <name>shoes</name>
        <pose>Unspecified</pose>
        <truncated>0</truncated>
        <difficult>0</difficult>
        <bndbox>
            <xmin>278</xmin>
            <ymin>542</ymin>
            <xmax>334</xmax>
            <ymax>567</ymax>
        </bndbox>
    </object>
</annotation>
